arb_analyzer/__init__.py
arb_analyzer/config.py
arb_analyzer/constants.py
arb_analyzer/context.py
arb_analyzer/exchanges/__init__.py
arb_analyzer/exchanges/base/__init__.py
arb_analyzer/exchanges/base/pool.py
arb_analyzer/exchanges/carbon_v1/__init__.py
arb_analyzer/exchanges/carbon_v1/pool.py
arb_analyzer/exchanges/carbon_v1/trade/impl.py
arb_analyzer/exchanges/carbon_v1/trade/spec.py
arb_analyzer/exchanges/uniswap_v3/__init__.py
arb_analyzer/exchanges/uniswap_v3/pool.py
arb_analyzer/exchanges/uniswap_v3/univ3calc.py
arb_analyzer/helpers/__init__.py
arb_analyzer/helpers/carbon_trade_splitter.py
arb_analyzer/helpers/routehandler.py
arb_analyzer/helpers/tradeinstruction.py
arb_analyzer/helpers/wrap_unwrap_processor.py
arb_analyzer/interfaces/__init__.py
arb_analyzer/interfaces/__main__.py
arb_analyzer/interfaces/input.py
arb_analyzer/interfaces/output.py
arb_analyzer/main.py
arb_analyzer/modes/__init__.py
arb_analyzer/modes/base.py
arb_analyzer/modes/base_pairwise.py
arb_analyzer/modes/base_triangle.py
arb_analyzer/modes/pairwise_all.py
arb_analyzer/modes/pairwise_pol.py
arb_analyzer/modes/triangle_all.py
arb_analyzer/modes/triangle_b3.py
arb_analyzer/modes/triangle_multi.py
arb_analyzer/runner.py
arb_analyzer-0.1.2.dist-info/METADATA
arb_analyzer-0.1.2.dist-info/WHEEL
arb_analyzer-0.1.2.dist-info/RECORD
