Metadata-Version: 2.1
Name: arb-analyzer
Version: 0.1.2
Summary: 
License: MIT
Author: Bancor Network
Author-email: services@bancor.network
Requires-Python: >=3.12,<4.0
Classifier: License :: OSI Approved :: MIT License
Classifier: Programming Language :: Python :: 3
Classifier: Programming Language :: Python :: 3.12
Requires-Dist: carb-optimizer (>=0.0.53,<0.0.54)
Requires-Dist: click (>=8.1.7,<9.0.0)
Requires-Dist: pydantic (>=2.7.0,<3.0.0)
